<?xml version="1.0" encoding="UTF-8" standalone="no"?><session><description>USER1 cammina verso la sedia da dx a sx (rispetto al kinect) e si siede</description><sample id="3" timestamp="1341761905002"><joint name="HEAD"><x>342.93576</x><y>89.90317</y><z>2135.5725</z><a>1.0</a></joint><joint name="NECK"><x>352.51385</x><y>153.20514</y><z>2145.6077</z><a>1.0</a></joint><joint name="TORSO"><x>350.31943</x><y>206.59671</y><z>2140.1868</z><a>1.0</a></joint><joint name="LEFT_SHOULDER"><x>334.95102</x><y>158.81572</y><z>2285.5115</z><a>1.0</a></joint><joint name="LEFT_ELBOW"><x>321.1274</x><y>224.67474</y><z>2313.2144</z><a>1.0</a></joint><joint name="LEFT_HAND"><x>274.59885</x><y>294.50687</y><z>2230.093</z><a>1.0</a></joint><joint name="RIGHT_SHOULDER"><x>372.52676</x><y>146.81184</y><z>2005.704</z><a>1.0</a></joint><joint name="RIGHT_ELBOW"><x>403.48196</x><y>207.25131</y><z>1994.6984</z><a>1.0</a></joint><joint name="RIGHT_HAND"><x>410.12268</x><y>288.2398</y><z>1921.2762</z><a>1.0</a></joint><joint name="LEFT_HIP"><x>336.75656</x><y>259.6404</y><z>2224.1807</z><a>1.0</a></joint><joint name="LEFT_KNEE"><x>343.27872</x><y>356.93735</y><z>2301.6985</z><a>1.0</a></joint><joint name="LEFT_FOOT"><x>380.38467</x><y>436.66666</y><z>2272.9065</z><a>1.0</a></joint><joint name="RIGHT_HIP"><x>360.4642</x><y>260.93256</y><z>2045.3508</z><a>1.0</a></joint><joint name="RIGHT_KNEE"><x>352.96057</x><y>372.71616</y><z>2031.3749</z><a>1.0</a></joint><joint name="RIGHT_FOOT"><x>370.5546</x><y>467.69226</y><z>2092.3933</z><a>1.0</a></joint></sample><sample id="3" timestamp="1341761905317"><joint name="HEAD"><x>342.52713</x><y>90.121704</y><z>2131.564</z><a>1.0</a></joint><joint name="NECK"><x>352.00787</x><y>154.60541</y><z>2131.3599</z><a>1.0</a></joint><joint name="TORSO"><x>350.1913</x><y>206.61768</y><z>2130.204</z><a>1.0</a></joint><joint name="LEFT_SHOULDER"><x>331.82077</x><y>158.7243</y><z>2252.2625</z><a>1.0</a></joint><joint name="LEFT_ELBOW"><x>321.36484</x><y>218.72002</y><z>2312.557</z><a>1.0</a></joint><joint name="LEFT_HAND"><x>278.24133</x><y>294.88104</y><z>2201.0386</z><a>1.0</a></joint><joint name="RIGHT_SHOULDER"><x>374.62296</x><y>149.9911</y><z>2010.4574</z><a>1.0</a></joint><joint name="RIGHT_ELBOW"><x>405.17303</x><y>210.95496</y><z>2026.3119</z><a>1.0</a></joint><joint name="RIGHT_HAND"><x>415.88864</x><y>296.24905</y><z>1949.3534</z><a>1.0</a></joint><joint name="LEFT_HIP"><x>334.19327</x><y>257.64505</y><z>2213.317</z><a>1.0</a></joint><joint name="LEFT_KNEE"><x>334.67328</x><y>356.37756</y><z>2254.7542</z><a>1.0</a></joint><joint name="LEFT_FOOT"><x>379.68347</x><y>438.83557</y><z>2249.5112</z><a>1.0</a></joint><joint name="RIGHT_HIP"><x>363.72104</x><y>259.8136</y><z>2044.7797</z><a>1.0</a></joint><joint name="RIGHT_KNEE"><x>354.4818</x><y>372.93347</y><z>2032.1077</z><a>1.0</a></joint><joint name="RIGHT_FOOT"><x>371.88986</x><y>468.02078</y><z>2090.0261</z><a>1.0</a></joint></sample><sample id="3" timestamp="1341761905618"><joint name="HEAD"><x>341.83304</x><y>90.21338</y><z>2124.5452</z><a>1.0</a></joint><joint name="NECK"><x>351.41953</x><y>154.51286</y><z>2124.83</z><a>1.0</a></joint><joint name="TORSO"><x>350.7071</x><y>206.3189</y><z>2122.7998</z><a>1.0</a></joint><joint name="LEFT_SHOULDER"><x>329.25204</x><y>158.75847</y><z>2235.6501</z><a>1.0</a></joint><joint name="LEFT_ELBOW"><x>321.51596</x><y>217.89995</y><z>2313.488</z><a>1.0</a></joint><joint name="LEFT_HAND"><x>295.81058</x><y>301.25266</y><z>2151.4934</z><a>1.0</a></joint><joint name="RIGHT_SHOULDER"><x>376.02652</x><y>149.80006</y><z>2014.0103</z><a>1.0</a></joint><joint name="RIGHT_ELBOW"><x>405.40543</x><y>210.14372</y><z>2041.6036</z><a>1.0</a></joint><joint name="RIGHT_HAND"><x>404.29477</x><y>292.26288</y><z>1977.2728</z><a>1.0</a></joint><joint name="LEFT_HIP"><x>334.55072</x><y>257.5984</y><z>2196.8738</z><a>1.0</a></joint><joint name="LEFT_KNEE"><x>333.09354</x><y>357.07324</y><z>2231.0698</z><a>1.0</a></joint><joint name="LEFT_FOOT"><x>375.69424</x><y>444.831</y><z>2236.9316</z><a>1.0</a></joint><joint name="RIGHT_HIP"><x>366.5854</x><y>258.8964</y><z>2044.665</z><a>1.0</a></joint><joint name="RIGHT_KNEE"><x>356.5003</x><y>372.37256</y><z>2035.4347</z><a>1.0</a></joint><joint name="RIGHT_FOOT"><x>373.2264</x><y>467.3764</y><z>2091.8652</z><a>1.0</a></joint></sample><sample id="3" timestamp="1341761905894"><joint name="HEAD"><x>339.31012</x><y>89.637924</y><z>2108.1438</z><a>1.0</a></joint><joint name="NECK"><x>350.1468</x><y>154.16457</y><z>2119.6045</z><a>1.0</a></joint><joint name="TORSO"><x>350.80124</x><y>206.15015</y><z>2115.088</z><a>1.0</a></joint><joint name="LEFT_SHOULDER"><x>328.15955</x><y>159.21959</y><z>2227.6838</z><a>1.0</a></joint><joint name="LEFT_ELBOW"><x>323.5856</x><y>222.9194</y><z>2291.2576</z><a>1.0</a></joint><joint name="LEFT_HAND"><x>298.53293</x><y>300.65063</y><z>2156.9385</z><a>1.0</a></joint><joint name="RIGHT_SHOULDER"><x>374.49683</x><y>148.56631</y><z>2011.5251</z><a>1.0</a></joint><joint name="RIGHT_ELBOW"><x>404.51038</x><y>207.74298</y><z>2037.7249</z><a>1.0</a></joint><joint name="RIGHT_HAND"><x>397.52005</x><y>289.21478</y><z>1917.229</z><a>1.0</a></joint><joint name="LEFT_HIP"><x>336.73892</x><y>258.3582</y><z>2181.2122</z><a>1.0</a></joint><joint name="LEFT_KNEE"><x>332.35275</x><y>358.19775</y><z>2217.2134</z><a>1.0</a></joint><joint name="LEFT_FOOT"><x>369.48233</x><y>443.8027</y><z>2247.1892</z><a>1.0</a></joint><joint name="RIGHT_HIP"><x>367.1975</x><y>258.3583</y><z>2039.9305</z><a>1.0</a></joint><joint name="RIGHT_KNEE"><x>356.5654</x><y>371.98224</y><z>2032.6461</z><a>1.0</a></joint><joint name="RIGHT_FOOT"><x>373.8545</x><y>466.88586</y><z>2092.3928</z><a>1.0</a></joint></sample><sample id="3" timestamp="1341761906324"><joint name="HEAD"><x>333.78693</x><y>88.66088</y><z>2095.7512</z><a>1.0</a></joint><joint name="NECK"><x>345.56046</x><y>155.2702</y><z>2103.312</z><a>1.0</a></joint><joint name="TORSO"><x>347.2189</x><y>208.29414</y><z>2104.979</z><a>1.0</a></joint><joint name="LEFT_SHOULDER"><x>327.0007</x><y>160.29686</y><z>2228.578</z><a>1.0</a></joint><joint name="LEFT_ELBOW"><x>326.15402</x><y>220.33899</y><z>2319.2644</z><a>1.0</a></joint><joint name="LEFT_HAND"><x>320.16385</x><y>285.4188</y><z>2362.2375</z><a>1.0</a></joint><joint name="RIGHT_SHOULDER"><x>366.47095</x><y>149.60689</y><z>1978.0463</z><a>1.0</a></joint><joint name="RIGHT_ELBOW"><x>389.91064</x><y>211.44333</y><z>1944.2714</z><a>1.0</a></joint><joint name="RIGHT_HAND"><x>360.9424</x><y>297.03665</y><z>1869.8235</z><a>1.0</a></joint><joint name="LEFT_HIP"><x>337.86813</x><y>260.68845</y><z>2178.5435</z><a>1.0</a></joint><joint name="LEFT_KNEE"><x>330.35236</x><y>361.90244</y><z>2195.4053</z><a>1.0</a></joint><joint name="LEFT_FOOT"><x>368.8856</x><y>441.82913</y><z>2274.9102</z><a>1.0</a></joint><joint name="RIGHT_HIP"><x>360.65915</x><y>261.81845</y><z>2034.7485</z><a>1.0</a></joint><joint name="RIGHT_KNEE"><x>355.54453</x><y>371.59555</y><z>2024.6598</z><a>1.0</a></joint><joint name="RIGHT_FOOT"><x>369.54782</x><y>468.95422</y><z>2080.0835</z><a>1.0</a></joint></sample><sample id="3" timestamp="1341761906661"><joint name="HEAD"><x>333.13818</x><y>88.99106</y><z>2094.8284</z><a>1.0</a></joint><joint name="NECK"><x>344.7609</x><y>156.23178</y><z>2095.7847</z><a>1.0</a></joint><joint name="TORSO"><x>345.67166</x><y>209.6995</y><z>2100.8733</z><a>1.0</a></joint><joint name="LEFT_SHOULDER"><x>327.58932</x><y>160.59808</y><z>2228.1326</z><a>1.0</a></joint><joint name="LEFT_ELBOW"><x>326.27994</x><y>220.44641</y><z>2318.9165</z><a>1.0</a></joint><joint name="LEFT_HAND"><x>321.94104</x><y>286.20755</y><z>2369.908</z><a>1.0</a></joint><joint name="RIGHT_SHOULDER"><x>364.2474</x><y>151.27687</y><z>1963.4369</z><a>1.0</a></joint><joint name="RIGHT_ELBOW"><x>388.59686</x><y>212.81644</y><z>1941.8434</z><a>1.0</a></joint><joint name="RIGHT_HAND"><x>371.1709</x><y>303.52713</y><z>1884.1315</z><a>1.0</a></joint><joint name="LEFT_HIP"><x>336.2899</x><y>261.73578</y><z>2183.1711</z><a>1.0</a></joint><joint name="LEFT_KNEE"><x>327.4213</x><y>364.50983</y><z>2184.7644</z><a>1.0</a></joint><joint name="LEFT_FOOT"><x>367.74988</x><y>442.1411</y><z>2279.2468</z><a>1.0</a></joint><joint name="RIGHT_HIP"><x>357.64923</x><y>264.17114</y><z>2028.7526</z><a>1.0</a></joint><joint name="RIGHT_KNEE"><x>355.19446</x><y>373.1899</y><z>2017.6659</z><a>1.0</a></joint><joint name="RIGHT_FOOT"><x>371.45517</x><y>466.9029</y><z>2082.9785</z><a>1.0</a></joint></sample><sample id="3" timestamp="1341761907073"><joint name="HEAD"><x>321.16397</x><y>89.95578</y><z>2091.9749</z><a>1.0</a></joint><joint name="NECK"><x>331.66464</x><y>157.47441</y><z>2097.6467</z><a>1.0</a></joint><joint name="TORSO"><x>328.687</x><y>210.40584</y><z>2091.3677</z><a>1.0</a></joint><joint name="LEFT_SHOULDER"><x>313.41852</x><y>162.4018</y><z>2227.9734</z><a>1.0</a></joint><joint name="LEFT_ELBOW"><x>321.37808</x><y>220.6924</y><z>2311.586</z><a>1.0</a></joint><joint name="LEFT_HAND"><x>311.6144</x><y>284.44766</y><z>2335.6428</z><a>1.0</a></joint><joint name="RIGHT_SHOULDER"><x>352.32822</x><y>151.8942</y><z>1967.3203</z><a>1.0</a></joint><joint name="RIGHT_ELBOW"><x>375.88638</x><y>216.32463</y><z>1946.685</z><a>1.0</a></joint><joint name="RIGHT_HAND"><x>348.9489</x><y>299.59528</y><z>1878.0862</z><a>1.0</a></joint><joint name="LEFT_HIP"><x>314.81635</x><y>262.87595</y><z>2161.9353</z><a>1.0</a></joint><joint name="LEFT_KNEE"><x>281.82852</x><y>371.16382</y><z>2019.0662</z><a>1.0</a></joint><joint name="LEFT_FOOT"><x>281.85825</x><y>468.8014</y><z>2102.7085</z><a>1.0</a></joint><joint name="RIGHT_HIP"><x>337.3988</x><y>264.49585</y><z>2008.2418</z><a>1.0</a></joint><joint name="RIGHT_KNEE"><x>339.52658</x><y>377.54236</y><z>2003.0736</z><a>1.0</a></joint><joint name="RIGHT_FOOT"><x>353.6447</x><y>467.86392</y><z>2095.93</z><a>1.0</a></joint></sample><sample id="3" timestamp="1341761907374"><joint name="HEAD"><x>277.6371</x><y>91.07835</y><z>2088.889</z><a>1.0</a></joint><joint name="NECK"><x>301.53668</x><y>158.0729</y><z>2124.0544</z><a>1.0</a></joint><joint name="TORSO"><x>298.3438</x><y>206.85216</y><z>2089.2202</z><a>1.0</a></joint><joint name="LEFT_SHOULDER"><x>274.87436</x><y>166.76239</y><z>2244.1033</z><a>1.0</a></joint><joint name="LEFT_ELBOW"><x>312.18726</x><y>224.58054</y><z>2315.869</z><a>1.0</a></joint><joint name="LEFT_HAND"><x>299.54684</x><y>288.24588</y><z>2333.73</z><a>1.0</a></joint><joint name="RIGHT_SHOULDER"><x>331.39334</x><y>148.34233</y><z>2004.0056</z><a>1.0</a></joint><joint name="RIGHT_ELBOW"><x>354.52698</x><y>213.84297</y><z>1974.2235</z><a>1.0</a></joint><joint name="RIGHT_HAND"><x>333.75342</x><y>286.83542</y><z>1896.8516</z><a>1.0</a></joint><joint name="LEFT_HIP"><x>280.7832</x><y>259.11832</y><z>2115.716</z><a>1.0</a></joint><joint name="LEFT_KNEE"><x>238.56114</x><y>365.39252</y><z>2042.5818</z><a>1.0</a></joint><joint name="LEFT_FOOT"><x>215.27945</x><y>461.20322</y><z>2125.958</z><a>1.0</a></joint><joint name="RIGHT_HIP"><x>310.1797</x><y>255.34016</y><z>1993.0559</z><a>1.0</a></joint><joint name="RIGHT_KNEE"><x>322.52185</x><y>366.87863</y><z>1982.4429</z><a>1.0</a></joint><joint name="RIGHT_FOOT"><x>345.54977</x><y>457.29425</y><z>2063.0771</z><a>1.0</a></joint></sample><sample id="3" timestamp="1341761907782"><joint name="HEAD"><x>233.19154</x><y>91.542984</y><z>2086.5137</z><a>1.0</a></joint><joint name="NECK"><x>247.00165</x><y>161.39827</y><z>2118.651</z><a>1.0</a></joint><joint name="TORSO"><x>250.0409</x><y>210.85301</y><z>2089.9658</z><a>1.0</a></joint><joint name="LEFT_SHOULDER"><x>224.50302</x><y>170.18286</y><z>2207.0022</z><a>1.0</a></joint><joint name="LEFT_ELBOW"><x>216.70822</x><y>219.4789</y><z>2280.2463</z><a>1.0</a></joint><joint name="LEFT_HAND"><x>305.68237</x><y>284.07965</y><z>2331.7163</z><a>1.0</a></joint><joint name="RIGHT_SHOULDER"><x>271.4584</x><y>151.84915</y><z>2030.2998</z><a>1.0</a></joint><joint name="RIGHT_ELBOW"><x>300.96933</x><y>215.86311</y><z>2063.179</z><a>1.0</a></joint><joint name="RIGHT_HAND"><x>303.57086</x><y>298.4663</y><z>1959.3145</z><a>1.0</a></joint><joint name="LEFT_HIP"><x>243.85733</x><y>263.63605</y><z>2095.6091</z><a>1.0</a></joint><joint name="LEFT_KNEE"><x>204.58722</x><y>364.48807</y><z>2057.8455</z><a>1.0</a></joint><joint name="LEFT_FOOT"><x>207.76721</x><y>457.73288</y><z>2135.998</z><a>1.0</a></joint><joint name="RIGHT_HIP"><x>262.78738</x><y>259.66623</y><z>2026.9521</z><a>1.0</a></joint><joint name="RIGHT_KNEE"><x>280.31406</x><y>362.52774</y><z>1974.8647</z><a>1.0</a></joint><joint name="RIGHT_FOOT"><x>335.27124</x><y>454.68765</y><z>2029.6294</z><a>1.0</a></joint></sample><sample id="3" timestamp="1341761908122"><joint name="HEAD"><x>187.19214</x><y>87.1108</y><z>2043.233</z><a>1.0</a></joint><joint name="NECK"><x>196.49239</x><y>154.85594</y><z>2098.9065</z><a>1.0</a></joint><joint name="TORSO"><x>200.57549</x><y>208.48497</y><z>2103.75</z><a>1.0</a></joint><joint name="LEFT_SHOULDER"><x>160.70477</x><y>158.68794</y><z>2133.4028</z><a>1.0</a></joint><joint name="LEFT_ELBOW"><x>157.59792</x><y>218.45396</y><z>2225.7656</z><a>1.0</a></joint><joint name="LEFT_HAND"><x>128.75343</x><y>307.72476</y><z>2117.4353</z><a>1.0</a></joint><joint name="RIGHT_SHOULDER"><x>233.47603</x><y>150.89589</y><z>2064.4104</z><a>1.0</a></joint><joint name="RIGHT_ELBOW"><x>249.2684</x><y>217.10677</y><z>2121.4763</z><a>1.0</a></joint><joint name="RIGHT_HAND"><x>243.26823</x><y>285.2064</y><z>1996.4689</z><a>1.0</a></joint><joint name="LEFT_HIP"><x>181.6711</x><y>263.21155</y><z>2130.6235</z><a>1.0</a></joint><joint name="LEFT_KNEE"><x>179.94093</x><y>368.49063</y><z>2058.5168</z><a>1.0</a></joint><joint name="LEFT_FOOT"><x>186.29381</x><y>455.7984</y><z>2164.1726</z><a>1.0</a></joint><joint name="RIGHT_HIP"><x>228.0936</x><y>260.49533</y><z>2086.5635</z><a>1.0</a></joint><joint name="RIGHT_KNEE"><x>227.78871</x><y>366.9231</y><z>1994.1252</z><a>1.0</a></joint><joint name="RIGHT_FOOT"><x>232.48804</x><y>453.56915</y><z>2110.9246</z><a>1.0</a></joint></sample><sample id="3" timestamp="1341761908479"><joint name="HEAD"><x>185.95105</x><y>90.188065</y><z>2062.2683</z><a>1.0</a></joint><joint name="NECK"><x>190.44257</x><y>159.5279</y><z>2126.9143</z><a>1.0</a></joint><joint name="TORSO"><x>193.91412</x><y>212.48613</y><z>2128.254</z><a>1.0</a></joint><joint name="LEFT_SHOULDER"><x>155.09319</x><y>162.34969</y><z>2140.9673</z><a>1.0</a></joint><joint name="LEFT_ELBOW"><x>151.85117</x><y>224.61195</y><z>2198.0012</z><a>1.0</a></joint><joint name="LEFT_HAND"><x>143.86607</x><y>294.31128</y><z>2053.0369</z><a>1.0</a></joint><joint name="RIGHT_SHOULDER"><x>226.26219</x><y>156.66858</y><z>2112.8616</z><a>1.0</a></joint><joint name="RIGHT_ELBOW"><x>240.16797</x><y>221.00745</y><z>2181.0398</z><a>1.0</a></joint><joint name="RIGHT_HAND"><x>244.29034</x><y>292.16827</y><z>2135.1992</z><a>1.0</a></joint><joint name="LEFT_HIP"><x>175.3617</x><y>266.70096</y><z>2138.3252</z><a>1.0</a></joint><joint name="LEFT_KNEE"><x>178.94606</x><y>374.8958</y><z>2077.978</z><a>1.0</a></joint><joint name="LEFT_FOOT"><x>189.77866</x><y>463.13763</y><z>2183.4556</z><a>1.0</a></joint><joint name="RIGHT_HIP"><x>219.58226</x><y>264.04358</y><z>2120.8618</z><a>1.0</a></joint><joint name="RIGHT_KNEE"><x>211.93126</x><y>377.00217</y><z>2089.1824</z><a>1.0</a></joint><joint name="RIGHT_FOOT"><x>210.51424</x><y>465.11563</y><z>2173.3293</z><a>1.0</a></joint></sample><sample id="3" timestamp="1341761908833"><joint name="HEAD"><x>191.27211</x><y>96.553856</y><z>2075.0247</z><a>1.0</a></joint><joint name="NECK"><x>191.5963</x><y>162.35634</y><z>2135.2756</z><a>1.0</a></joint><joint name="TORSO"><x>195.75279</x><y>214.91693</y><z>2149.5012</z><a>1.0</a></joint><joint name="LEFT_SHOULDER"><x>155.36607</x><y>164.97372</y><z>2150.8267</z><a>1.0</a></joint><joint name="LEFT_ELBOW"><x>152.45262</x><y>228.59915</y><z>2215.3254</z><a>1.0</a></joint><joint name="LEFT_HAND"><x>146.99048</x><y>303.59976</y><z>2080.8162</z><a>1.0</a></joint><joint name="RIGHT_SHOULDER"><x>228.35814</x><y>159.70058</y><z>2119.7249</z><a>1.0</a></joint><joint name="RIGHT_ELBOW"><x>242.1024</x><y>222.4338</y><z>2213.7407</z><a>1.0</a></joint><joint name="RIGHT_HAND"><x>247.61057</x><y>296.6204</y><z>2136.5989</z><a>1.0</a></joint><joint name="LEFT_HIP"><x>178.21031</x><y>267.89713</y><z>2173.0977</z><a>1.0</a></joint><joint name="LEFT_KNEE"><x>179.88548</x><y>377.98697</y><z>2083.6704</z><a>1.0</a></joint><joint name="LEFT_FOOT"><x>190.55818</x><y>467.65033</y><z>2187.5752</z><a>1.0</a></joint><joint name="RIGHT_HIP"><x>221.68726</x><y>265.666</y><z>2154.3557</z><a>1.0</a></joint><joint name="RIGHT_KNEE"><x>210.74274</x><y>371.095</y><z>2111.2175</z><a>1.0</a></joint><joint name="RIGHT_FOOT"><x>208.25961</x><y>463.55783</y><z>2176.9297</z><a>1.0</a></joint></sample><sample id="3" timestamp="1341761908939"><joint name="HEAD"><x>194.02882</x><y>129.42253</y><z>2013.9745</z><a>1.0</a></joint><joint name="NECK"><x>196.88307</x><y>182.26494</y><z>2108.8367</z><a>1.0</a></joint><joint name="TORSO"><x>200.0298</x><y>229.24298</y><z>2158.424</z><a>1.0</a></joint><joint name="LEFT_SHOULDER"><x>161.68556</x><y>182.67664</y><z>2105.6016</z><a>1.0</a></joint><joint name="LEFT_ELBOW"><x>152.10962</x><y>229.42772</y><z>2206.0396</z><a>1.0</a></joint><joint name="LEFT_HAND"><x>143.0223</x><y>310.84113</y><z>2149.628</z><a>1.0</a></joint><joint name="RIGHT_SHOULDER"><x>231.97273</x><y>181.85449</y><z>2112.0715</z><a>1.0</a></joint><joint name="RIGHT_ELBOW"><x>243.95724</x><y>242.3373</y><z>2199.5354</z><a>1.0</a></joint><joint name="RIGHT_HAND"><x>243.3383</x><y>312.78683</y><z>2143.887</z><a>1.0</a></joint><joint name="LEFT_HIP"><x>179.69417</x><y>274.47766</y><z>2205.7637</z><a>1.0</a></joint><joint name="LEFT_KNEE"><x>178.15929</x><y>378.73785</y><z>2074.506</z><a>1.0</a></joint><joint name="LEFT_FOOT"><x>189.029</x><y>468.18817</y><z>2177.333</z><a>1.0</a></joint><joint name="RIGHT_HIP"><x>226.32878</x><y>273.745</y><z>2210.2595</z><a>1.0</a></joint><joint name="RIGHT_KNEE"><x>211.5136</x><y>372.37988</y><z>2126.9275</z><a>1.0</a></joint><joint name="RIGHT_FOOT"><x>206.00168</x><y>469.45065</y><z>2194.8027</z><a>1.0</a></joint></sample><sample id="3" timestamp="1341761909076"><joint name="HEAD"><x>191.54396</x><y>151.24892</y><z>1987.819</z><a>1.0</a></joint><joint name="NECK"><x>196.51202</x><y>210.49287</y><z>2094.8972</z><a>1.0</a></joint><joint name="TORSO"><x>203.52733</x><y>252.22104</y><z>2174.9985</z><a>1.0</a></joint><joint name="LEFT_SHOULDER"><x>160.89766</x><y>212.53526</y><z>2095.8508</z><a>1.0</a></joint><joint name="LEFT_ELBOW"><x>149.73692</x><y>264.5754</y><z>2208.6262</z><a>1.0</a></joint><joint name="LEFT_HAND"><x>140.87563</x><y>358.17447</y><z>2192.0876</z><a>1.0</a></joint><joint name="RIGHT_SHOULDER"><x>232.15883</x><y>208.44862</y><z>2093.9438</z><a>1.0</a></joint><joint name="RIGHT_ELBOW"><x>240.2989</x><y>270.08728</y><z>2175.8792</z><a>1.0</a></joint><joint name="RIGHT_HAND"><x>227.87186</x><y>343.5507</y><z>2101.6262</z><a>1.0</a></joint><joint name="LEFT_HIP"><x>186.10164</x><y>292.33304</y><z>2255.7896</z><a>1.0</a></joint><joint name="LEFT_KNEE"><x>174.25552</x><y>383.8248</y><z>2086.2092</z><a>1.0</a></joint><joint name="LEFT_FOOT"><x>187.51654</x><y>474.03925</y><z>2189.6091</z><a>1.0</a></joint><joint name="RIGHT_HIP"><x>234.00154</x><y>289.6358</y><z>2254.41</z><a>1.0</a></joint><joint name="RIGHT_KNEE"><x>212.88655</x><y>370.56967</y><z>2113.5583</z><a>1.0</a></joint><joint name="RIGHT_FOOT"><x>214.56418</x><y>461.49878</y><z>2217.048</z><a>1.0</a></joint></sample><sample id="3" timestamp="1341761909179"><joint name="HEAD"><x>185.8438</x><y>170.97816</y><z>1976.135</z><a>1.0</a></joint><joint name="NECK"><x>190.61276</x><y>228.95036</y><z>2092.4863</z><a>1.0</a></joint><joint name="TORSO"><x>197.7959</x><y>266.9983</y><z>2198.4954</z><a>1.0</a></joint><joint name="LEFT_SHOULDER"><x>157.28783</x><y>228.66457</y><z>2098.2153</z><a>1.0</a></joint><joint name="LEFT_ELBOW"><x>147.17937</x><y>282.0582</y><z>2207.5469</z><a>1.0</a></joint><joint name="LEFT_HAND"><x>143.13391</x><y>377.90945</y><z>2238.2947</z><a>1.0</a></joint><joint name="RIGHT_SHOULDER"><x>224.1207</x><y>229.23773</y><z>2086.7573</z><a>1.0</a></joint><joint name="RIGHT_ELBOW"><x>237.39119</x><y>289.23856</y><z>2181.6987</z><a>1.0</a></joint><joint name="RIGHT_HAND"><x>238.87949</x><y>374.4827</y><z>2166.69</z><a>1.0</a></joint><joint name="LEFT_HIP"><x>178.93231</x><y>301.17743</y><z>2309.3022</z><a>1.0</a></joint><joint name="LEFT_KNEE"><x>172.67897</x><y>379.46954</y><z>2080.462</z><a>1.0</a></joint><joint name="LEFT_FOOT"><x>186.13313</x><y>474.86035</y><z>2195.7524</z><a>1.0</a></joint><joint name="RIGHT_HIP"><x>229.80998</x><y>301.91556</y><z>2299.7065</z><a>1.0</a></joint><joint name="RIGHT_KNEE"><x>201.84367</x><y>392.4769</y><z>2085.1548</z><a>1.0</a></joint><joint name="RIGHT_FOOT"><x>205.16893</x><y>472.4473</y><z>2193.1565</z><a>1.0</a></joint></sample><sample id="3" timestamp="1341761909257"><joint name="HEAD"><x>183.06053</x><y>185.92471</y><z>1968.5326</z><a>1.0</a></joint><joint name="NECK"><x>189.24387</x><y>240.28903</y><z>2088.168</z><a>1.0</a></joint><joint name="TORSO"><x>187.3061</x><y>286.19022</y><z>2154.4834</z><a>1.0</a></joint><joint name="LEFT_SHOULDER"><x>159.42497</x><y>233.46017</y><z>2114.2573</z><a>1.0</a></joint><joint name="LEFT_ELBOW"><x>150.53517</x><y>286.08847</y><z>2229.3992</z><a>1.0</a></joint><joint name="LEFT_HAND"><x>152.43285</x><y>357.66415</y><z>2279.8552</z><a>1.0</a></joint><joint name="RIGHT_SHOULDER"><x>219.8173</x><y>247.29066</y><z>2062.0784</z><a>1.0</a></joint><joint name="RIGHT_ELBOW"><x>228.09077</x><y>301.7364</y><z>2185.9268</z><a>1.0</a></joint><joint name="RIGHT_HAND"><x>227.97198</x><y>374.82495</y><z>2125.6248</z><a>1.0</a></joint><joint name="LEFT_HIP"><x>163.84898</x><y>323.5891</y><z>2240.893</z><a>1.0</a></joint><joint name="LEFT_KNEE"><x>153.84511</x><y>432.9798</y><z>2144.241</z><a>1.0</a></joint><joint name="LEFT_FOOT"><x>175.76353</x><y>501.7832</y><z>2275.5352</z><a>1.0</a></joint><joint name="RIGHT_HIP"><x>207.51428</x><y>335.2163</y><z>2200.7048</z><a>1.0</a></joint><joint name="RIGHT_KNEE"><x>207.61287</x><y>429.13312</y><z>2118.5083</z><a>1.0</a></joint><joint name="RIGHT_FOOT"><x>210.1006</x><y>476.76318</y><z>2230.9463</z><a>1.0</a></joint></sample><sample id="3" timestamp="1341761909384"><joint name="HEAD"><x>181.37932</x><y>192.70135</y><z>1963.3104</z><a>1.0</a></joint><joint name="NECK"><x>187.9726</x><y>246.1724</y><z>2089.7717</z><a>1.0</a></joint><joint name="TORSO"><x>187.02324</x><y>290.91028</y><z>2163.442</z><a>1.0</a></joint><joint name="LEFT_SHOULDER"><x>155.75511</x><y>241.41699</y><z>2096.309</z><a>1.0</a></joint><joint name="LEFT_ELBOW"><x>148.00774</x><y>290.87445</y><z>2223.058</z><a>1.0</a></joint><joint name="LEFT_HAND"><x>143.9351</x><y>376.1332</y><z>2181.5195</z><a>1.0</a></joint><joint name="RIGHT_SHOULDER"><x>220.39229</x><y>250.95764</y><z>2083.2346</z><a>1.0</a></joint><joint name="RIGHT_ELBOW"><x>228.47021</x><y>300.14606</y><z>2227.8938</z><a>1.0</a></joint><joint name="RIGHT_HAND"><x>237.78677</x><y>375.0583</y><z>2191.8826</z><a>1.0</a></joint><joint name="LEFT_HIP"><x>166.63957</x><y>329.66003</y><z>2241.3425</z><a>1.0</a></joint><joint name="LEFT_KNEE"><x>165.32785</x><y>429.54996</y><z>2261.998</z><a>1.0</a></joint><joint name="LEFT_FOOT"><x>179.54723</x><y>495.61636</y><z>2308.365</z><a>1.0</a></joint><joint name="RIGHT_HIP"><x>205.7071</x><y>335.75482</y><z>2232.8813</z><a>1.0</a></joint><joint name="RIGHT_KNEE"><x>201.1597</x><y>434.6618</y><z>2089.4575</z><a>1.0</a></joint><joint name="RIGHT_FOOT"><x>203.16594</x><y>493.23633</y><z>2209.9236</z><a>1.0</a></joint></sample><sample id="3" timestamp="1341761909457"><joint name="HEAD"><x>177.32756</x><y>198.75514</y><z>2000.9292</z><a>1.0</a></joint><joint name="NECK"><x>186.14587</x><y>250.58014</y><z>2108.395</z><a>1.0</a></joint><joint name="TORSO"><x>188.95338</x><y>294.61343</y><z>2178.8513</z><a>1.0</a></joint><joint name="LEFT_SHOULDER"><x>154.56908</x><y>246.76418</y><z>2131.083</z><a>1.0</a></joint><joint name="LEFT_ELBOW"><x>148.09311</x><y>293.831</y><z>2243.7</z><a>1.0</a></joint><joint name="LEFT_HAND"><x>141.83812</x><y>378.22885</y><z>2176.3843</z><a>1.0</a></joint><joint name="RIGHT_SHOULDER"><x>218.40962</x><y>254.47911</y><z>2085.7068</z><a>1.0</a></joint><joint name="RIGHT_ELBOW"><x>229.33775</x><y>300.00623</y><z>2240.3914</z><a>1.0</a></joint><joint name="RIGHT_HAND"><x>236.74924</x><y>374.1562</y><z>2190.9846</z><a>1.0</a></joint><joint name="LEFT_HIP"><x>172.6831</x><y>333.06543</y><z>2263.7078</z><a>1.0</a></joint><joint name="LEFT_KNEE"><x>167.87715</x><y>433.37198</y><z>2263.4326</z><a>1.0</a></joint><joint name="LEFT_FOOT"><x>180.14473</x><y>501.5306</y><z>2318.622</z><a>1.0</a></joint><joint name="RIGHT_HIP"><x>210.73053</x><y>338.74725</y><z>2234.9077</z><a>1.0</a></joint><joint name="RIGHT_KNEE"><x>193.32872</x><y>434.68753</y><z>2072.5293</z><a>1.0</a></joint><joint name="RIGHT_FOOT"><x>201.6214</x><y>498.1096</y><z>2200.7039</z><a>1.0</a></joint></sample><sample id="3" timestamp="1341761909529"><joint name="HEAD"><x>176.53963</x><y>199.49597</y><z>2005.8416</z><a>1.0</a></joint><joint name="NECK"><x>185.80756</x><y>251.6255</y><z>2118.6848</z><a>1.0</a></joint><joint name="TORSO"><x>190.08966</x><y>297.34573</y><z>2185.3018</z><a>1.0</a></joint><joint name="LEFT_SHOULDER"><x>154.41867</x><y>248.51897</y><z>2148.8694</z><a>1.0</a></joint><joint name="LEFT_ELBOW"><x>153.20369</x><y>299.40912</y><z>2279.8887</z><a>1.0</a></joint><joint name="LEFT_HAND"><x>142.3787</x><y>378.68567</y><z>2182.7312</z><a>1.0</a></joint><joint name="RIGHT_SHOULDER"><x>218.10376</x><y>254.82185</y><z>2088.5002</z><a>1.0</a></joint><joint name="RIGHT_ELBOW"><x>232.66531</x><y>298.37885</y><z>2268.257</z><a>1.0</a></joint><joint name="RIGHT_HAND"><x>237.63402</x><y>374.90707</y><z>2189.2559</z><a>1.0</a></joint><joint name="LEFT_HIP"><x>176.31317</x><y>337.90088</y><z>2269.9385</z><a>1.0</a></joint><joint name="LEFT_KNEE"><x>168.80298</x><y>432.044</y><z>2260.342</z><a>1.0</a></joint><joint name="LEFT_FOOT"><x>182.18756</x><y>501.36752</y><z>2325.4636</z><a>1.0</a></joint><joint name="RIGHT_HIP"><x>212.21089</x><y>342.8607</y><z>2233.899</z><a>1.0</a></joint><joint name="RIGHT_KNEE"><x>194.9418</x><y>434.87128</y><z>2071.5066</z><a>1.0</a></joint><joint name="RIGHT_FOOT"><x>201.82782</x><y>498.53284</y><z>2210.3157</z><a>1.0</a></joint></sample><sample id="3" timestamp="1341761909649"><joint name="HEAD"><x>176.63959</x><y>201.96559</y><z>2064.9756</z><a>1.0</a></joint><joint name="NECK"><x>184.4449</x><y>253.11743</y><z>2165.835</z><a>1.0</a></joint><joint name="TORSO"><x>189.22888</x><y>298.37244</y><z>2220.4587</z><a>1.0</a></joint><joint name="LEFT_SHOULDER"><x>154.42651</x><y>251.18</y><z>2199.715</z><a>1.0</a></joint><joint name="LEFT_ELBOW"><x>155.9896</x><y>299.50638</y><z>2338.1816</z><a>1.0</a></joint><joint name="LEFT_HAND"><x>147.13905</x><y>377.7633</y><z>2200.8748</z><a>1.0</a></joint><joint name="RIGHT_SHOULDER"><x>215.41737</x><y>255.11644</y><z>2131.955</z><a>1.0</a></joint><joint name="RIGHT_ELBOW"><x>241.31491</x><y>296.06714</y><z>2291.8057</z><a>1.0</a></joint><joint name="RIGHT_HAND"><x>236.87527</x><y>373.3055</y><z>2175.1555</z><a>1.0</a></joint><joint name="LEFT_HIP"><x>176.98564</x><y>339.61768</y><z>2294.7656</z><a>1.0</a></joint><joint name="LEFT_KNEE"><x>172.38615</x><y>433.70953</y><z>2290.1667</z><a>1.0</a></joint><joint name="LEFT_FOOT"><x>187.56284</x><y>505.01465</y><z>2363.3357</z><a>1.0</a></joint><joint name="RIGHT_HIP"><x>210.8738</x><y>343.3231</y><z>2255.3992</z><a>1.0</a></joint><joint name="RIGHT_KNEE"><x>196.99634</x><y>434.57425</y><z>2049.229</z><a>1.0</a></joint><joint name="RIGHT_FOOT"><x>204.53468</x><y>501.7957</y><z>2201.0913</z><a>1.0</a></joint></sample><sample id="3" timestamp="1341761909777"><joint name="HEAD"><x>178.92181</x><y>198.85194</y><z>2117.3613</z><a>1.0</a></joint><joint name="NECK"><x>184.58797</x><y>252.12695</y><z>2196.0864</z><a>1.0</a></joint><joint name="TORSO"><x>189.12865</x><y>298.11703</y><z>2239.6138</z><a>1.0</a></joint><joint name="LEFT_SHOULDER"><x>154.4333</x><y>250.99738</y><z>2232.414</z><a>1.0</a></joint><joint name="LEFT_ELBOW"><x>156.20067</x><y>299.66483</y><z>2364.5227</z><a>1.0</a></joint><joint name="LEFT_HAND"><x>144.78362</x><y>379.07266</y><z>2191.6687</z><a>1.0</a></joint><joint name="RIGHT_SHOULDER"><x>215.75706</x><y>253.29453</y><z>2159.7588</z><a>1.0</a></joint><joint name="RIGHT_ELBOW"><x>242.97575</x><y>294.25314</y><z>2304.29</z><a>1.0</a></joint><joint name="RIGHT_HAND"><x>237.35622</x><y>373.1896</y><z>2171.1863</z><a>1.0</a></joint><joint name="LEFT_HIP"><x>176.79695</x><y>340.92178</y><z>2303.803</z><a>1.0</a></joint><joint name="LEFT_KNEE"><x>173.96585</x><y>435.9767</y><z>2310.3225</z><a>1.0</a></joint><joint name="LEFT_FOOT"><x>193.05545</x><y>506.7049</y><z>2403.151</z><a>1.0</a></joint><joint name="RIGHT_HIP"><x>210.50044</x><y>343.81143</y><z>2262.4795</z><a>1.0</a></joint><joint name="RIGHT_KNEE"><x>197.90611</x><y>432.6398</y><z>2050.9583</z><a>1.0</a></joint><joint name="RIGHT_FOOT"><x>205.5698</x><y>500.49606</y><z>2215.0068</z><a>1.0</a></joint></sample><sample id="3" timestamp="1341761909853"><joint name="HEAD"><x>183.66994</x><y>198.67572</y><z>2176.5522</z><a>1.0</a></joint><joint name="NECK"><x>187.45212</x><y>251.96065</y><z>2242.243</z><a>1.0</a></joint><joint name="TORSO"><x>193.07883</x><y>297.57126</y><z>2279.891</z><a>1.0</a></joint><joint name="LEFT_SHOULDER"><x>156.78146</x><y>252.72076</y><z>2271.0522</z><a>1.0</a></joint><joint name="LEFT_ELBOW"><x>156.72243</x><y>301.13373</y><z>2372.709</z><a>1.0</a></joint><joint name="LEFT_HAND"><x>146.32562</x><y>373.6233</y><z>2219.7073</z><a>1.0</a></joint><joint name="RIGHT_SHOULDER"><x>218.92117</x><y>251.18074</y><z>2213.4338</z><a>1.0</a></joint><joint name="RIGHT_ELBOW"><x>245.92319</x><y>293.26086</y><z>2322.9927</z><a>1.0</a></joint><joint name="RIGHT_HAND"><x>239.73964</x><y>368.77313</y><z>2192.7463</z><a>1.0</a></joint><joint name="LEFT_HIP"><x>181.4204</x><y>341.49005</y><z>2333.9734</z><a>1.0</a></joint><joint name="LEFT_KNEE"><x>176.94098</x><y>435.49826</y><z>2336.8743</z><a>1.0</a></joint><joint name="LEFT_FOOT"><x>195.37437</x><y>507.47073</y><z>2419.8967</z><a>1.0</a></joint><joint name="RIGHT_HIP"><x>215.86935</x><y>341.91296</y><z>2301.105</z><a>1.0</a></joint><joint name="RIGHT_KNEE"><x>197.6316</x><y>423.5679</y><z>2036.5588</z><a>1.0</a></joint><joint name="RIGHT_FOOT"><x>207.24542</x><y>499.1937</y><z>2211.6926</z><a>1.0</a></joint></sample><sample id="3" timestamp="1341761909958"><joint name="HEAD"><x>187.202</x><y>197.77698</y><z>2222.6353</z><a>1.0</a></joint><joint name="NECK"><x>193.4841</x><y>249.9968</y><z>2286.8574</z><a>1.0</a></joint><joint name="TORSO"><x>199.33565</x><y>293.97467</y><z>2328.4229</z><a>1.0</a></joint><joint name="LEFT_SHOULDER"><x>163.36488</x><y>250.91333</y><z>2313.3967</z><a>1.0</a></joint><joint name="LEFT_ELBOW"><x>163.3875</x><y>299.14804</y><z>2422.9434</z><a>1.0</a></joint><joint name="LEFT_HAND"><x>148.37881</x><y>373.375</y><z>2220.021</z><a>1.0</a></joint><joint name="RIGHT_SHOULDER"><x>224.31062</x><y>249.05876</y><z>2260.3184</z><a>1.0</a></joint><joint name="RIGHT_ELBOW"><x>248.74615</x><y>294.84695</y><z>2346.9294</z><a>1.0</a></joint><joint name="RIGHT_HAND"><x>240.22685</x><y>366.34778</y><z>2191.334</z><a>1.0</a></joint><joint name="LEFT_HIP"><x>187.6977</x><y>336.36722</y><z>2385.625</z><a>1.0</a></joint><joint name="LEFT_KNEE"><x>178.93762</x><y>434.5122</y><z>2349.1455</z><a>1.0</a></joint><joint name="LEFT_FOOT"><x>195.77647</x><y>508.21838</y><z>2413.9075</z><a>1.0</a></joint><joint name="RIGHT_HIP"><x>222.49576</x><y>336.45328</y><z>2354.3513</z><a>1.0</a></joint><joint name="RIGHT_KNEE"><x>202.87817</x><y>410.29434</y><z>2028.6317</z><a>1.0</a></joint><joint name="RIGHT_FOOT"><x>208.83488</x><y>480.52777</y><z>2222.9558</z><a>1.0</a></joint></sample><sample id="3" timestamp="1341761910050"><joint name="HEAD"><x>194.76836</x><y>196.56516</y><z>2295.84</z><a>1.0</a></joint><joint name="NECK"><x>201.13133</x><y>250.38478</y><z>2338.2517</z><a>1.0</a></joint><joint name="TORSO"><x>204.01616</x><y>294.05966</y><z>2361.608</z><a>1.0</a></joint><joint name="LEFT_SHOULDER"><x>171.74382</x><y>250.88594</y><z>2357.1387</z><a>1.0</a></joint><joint name="LEFT_ELBOW"><x>165.797</x><y>299.1036</y><z>2440.6345</z><a>1.0</a></joint><joint name="LEFT_HAND"><x>150.67383</x><y>373.0089</y><z>2207.8335</z><a>1.0</a></joint><joint name="RIGHT_SHOULDER"><x>230.99745</x><y>249.87544</y><z>2319.3645</z><a>1.0</a></joint><joint name="RIGHT_ELBOW"><x>249.74718</x><y>303.03357</y><z>2374.5833</z><a>1.0</a></joint><joint name="RIGHT_HAND"><x>240.03732</x><y>371.34207</y><z>2192.057</z><a>1.0</a></joint><joint name="LEFT_HIP"><x>188.9064</x><y>336.76215</y><z>2396.668</z><a>1.0</a></joint><joint name="LEFT_KNEE"><x>180.50284</x><y>434.1018</y><z>2358.7173</z><a>1.0</a></joint><joint name="LEFT_FOOT"><x>200.19069</x><y>506.96976</y><z>2432.0505</z><a>1.0</a></joint><joint name="RIGHT_HIP"><x>224.9595</x><y>336.9972</y><z>2373.2605</z><a>1.0</a></joint><joint name="RIGHT_KNEE"><x>202.61517</x><y>408.61533</y><z>2031.0455</z><a>1.0</a></joint><joint name="RIGHT_FOOT"><x>208.95116</x><y>479.2522</y><z>2212.3054</z><a>1.0</a></joint></sample><sample id="3" timestamp="1341761910140"><joint name="HEAD"><x>198.15176</x><y>197.68813</y><z>2335.9019</z><a>1.0</a></joint><joint name="NECK"><x>204.00113</x><y>250.86179</y><z>2366.487</z><a>1.0</a></joint><joint name="TORSO"><x>206.13332</x><y>294.29037</y><z>2381.5935</z><a>1.0</a></joint><joint name="LEFT_SHOULDER"><x>175.40292</x><y>251.32281</y><z>2386.1418</z><a>1.0</a></joint><joint name="LEFT_ELBOW"><x>166.73741</x><y>299.25336</y><z>2446.1973</z><a>1.0</a></joint><joint name="LEFT_HAND"><x>152.0448</x><y>381.07977</y><z>2194.794</z><a>1.0</a></joint><joint name="RIGHT_SHOULDER"><x>233.07837</x><y>250.39304</y><z>2346.8323</z><a>1.0</a></joint><joint name="RIGHT_ELBOW"><x>250.37564</x><y>305.04056</y><z>2388.7937</z><a>1.0</a></joint><joint name="RIGHT_HAND"><x>240.89346</x><y>373.6459</y><z>2189.4778</z><a>1.0</a></joint><joint name="LEFT_HIP"><x>190.16013</x><y>337.0137</y><z>2409.2297</z><a>1.0</a></joint><joint name="LEFT_KNEE"><x>183.44781</x><y>433.4019</y><z>2371.107</z><a>1.0</a></joint><joint name="LEFT_FOOT"><x>203.66661</x><y>505.91083</y><z>2436.0342</z><a>1.0</a></joint><joint name="RIGHT_HIP"><x>226.50713</x><y>337.33093</y><z>2384.1702</z><a>1.0</a></joint><joint name="RIGHT_KNEE"><x>201.53088</x><y>405.0805</y><z>2029.9572</z><a>1.0</a></joint><joint name="RIGHT_FOOT"><x>209.81909</x><y>480.61597</y><z>2192.346</z><a>1.0</a></joint></sample><sample id="3" timestamp="1341761910212"><joint name="HEAD"><x>201.15527</x><y>198.07745</y><z>2365.9468</z><a>1.0</a></joint><joint name="NECK"><x>205.06792</x><y>249.91214</y><z>2387.077</z><a>1.0</a></joint><joint name="TORSO"><x>207.3916</x><y>293.10568</y><z>2393.8296</z><a>1.0</a></joint><joint name="LEFT_SHOULDER"><x>177.26651</x><y>251.00168</y><z>2405.0989</z><a>1.0</a></joint><joint name="LEFT_ELBOW"><x>168.26796</x><y>298.5361</y><z>2454.123</z><a>1.0</a></joint><joint name="LEFT_HAND"><x>169.71361</x><y>358.5839</y><z>2223.8105</z><a>1.0</a></joint><joint name="RIGHT_SHOULDER"><x>233.29233</x><y>248.80602</y><z>2369.0552</z><a>1.0</a></joint><joint name="RIGHT_ELBOW"><x>249.91809</x><y>303.64886</y><z>2390.1992</z><a>1.0</a></joint><joint name="RIGHT_HAND"><x>242.267</x><y>372.3999</y><z>2202.9878</z><a>1.0</a></joint><joint name="LEFT_HIP"><x>191.586</x><y>336.34525</y><z>2412.3464</z><a>1.0</a></joint><joint name="LEFT_KNEE"><x>192.91847</x><y>425.36844</y><z>2441.48</z><a>1.0</a></joint><joint name="LEFT_FOOT"><x>202.19986</x><y>505.08377</y><z>2418.6216</z><a>1.0</a></joint><joint name="RIGHT_HIP"><x>227.99687</x><y>335.7644</y><z>2388.8179</z><a>1.0</a></joint><joint name="RIGHT_KNEE"><x>202.15083</x><y>401.43317</y><z>2034.4037</z><a>1.0</a></joint><joint name="RIGHT_FOOT"><x>210.41742</x><y>477.87112</y><z>2184.7136</z><a>1.0</a></joint></sample><sample id="3" timestamp="1341761910302"><joint name="HEAD"><x>203.0366</x><y>197.70444</y><z>2382.951</z><a>1.0</a></joint><joint name="NECK"><x>205.90643</x><y>248.967</y><z>2397.6123</z><a>1.0</a></joint><joint name="TORSO"><x>208.15942</x><y>292.33853</y><z>2399.4404</z><a>1.0</a></joint><joint name="LEFT_SHOULDER"><x>177.82811</x><y>250.3213</y><z>2410.2695</z><a>1.0</a></joint><joint name="LEFT_ELBOW"><x>168.90579</x><y>297.82922</y><z>2458.1814</z><a>1.0</a></joint><joint name="LEFT_HAND"><x>163.53348</x><y>371.18875</y><z>2181.4106</z><a>1.0</a></joint><joint name="RIGHT_SHOULDER"><x>234.28279</x><y>247.59831</y><z>2384.9553</z><a>1.0</a></joint><joint name="RIGHT_ELBOW"><x>249.89749</x><y>303.61407</y><z>2388.8896</z><a>1.0</a></joint><joint name="RIGHT_HAND"><x>242.0091</x><y>372.30716</y><z>2196.215</z><a>1.0</a></joint><joint name="LEFT_HIP"><x>191.97998</x><y>336.2337</y><z>2409.5664</z><a>1.0</a></joint><joint name="LEFT_KNEE"><x>192.79279</x><y>426.0736</y><z>2439.707</z><a>1.0</a></joint><joint name="LEFT_FOOT"><x>199.44667</x><y>502.61578</y><z>2393.7651</z><a>1.0</a></joint><joint name="RIGHT_HIP"><x>228.96579</x><y>335.05032</y><z>2392.9705</z><a>1.0</a></joint><joint name="RIGHT_KNEE"><x>202.91891</x><y>400.171</y><z>2036.941</z><a>1.0</a></joint><joint name="RIGHT_FOOT"><x>209.79947</x><y>477.171</y><z>2182.6868</z><a>1.0</a></joint></sample><sample id="3" timestamp="1341761910385"><joint name="HEAD"><x>204.64508</x><y>197.76947</y><z>2411.9268</z><a>1.0</a></joint><joint name="NECK"><x>207.13066</x><y>248.32782</y><z>2409.822</z><a>1.0</a></joint><joint name="TORSO"><x>209.19962</x><y>291.64032</y><z>2406.6108</z><a>1.0</a></joint><joint name="LEFT_SHOULDER"><x>179.42285</x><y>249.78706</y><z>2422.1255</z><a>1.0</a></joint><joint name="LEFT_ELBOW"><x>169.33977</x><y>298.3075</y><z>2460.8406</z><a>1.0</a></joint><joint name="LEFT_HAND"><x>153.10782</x><y>371.68417</y><z>2216.719</z><a>1.0</a></joint><joint name="RIGHT_SHOULDER"><x>235.12283</x><y>246.8536</y><z>2397.5183</z><a>1.0</a></joint><joint name="RIGHT_ELBOW"><x>250.73018</x><y>302.65973</y><z>2390.4932</z><a>1.0</a></joint><joint name="RIGHT_HAND"><x>241.7782</x><y>374.01675</y><z>2200.1646</z><a>1.0</a></joint><joint name="LEFT_HIP"><x>192.53961</x><y>335.75677</y><z>2411.6765</z><a>1.0</a></joint><joint name="LEFT_KNEE"><x>192.2101</x><y>426.24295</y><z>2432.7974</z><a>1.0</a></joint><joint name="LEFT_FOOT"><x>189.94615</x><y>477.85266</y><z>2226.8823</z><a>1.0</a></joint><joint name="RIGHT_HIP"><x>230.13808</x><y>334.37558</y><z>2395.123</z><a>1.0</a></joint><joint name="RIGHT_KNEE"><x>204.28275</x><y>398.86</y><z>2039.486</z><a>1.0</a></joint><joint name="RIGHT_FOOT"><x>206.89987</x><y>475.14774</y><z>2171.3677</z><a>1.0</a></joint></sample><sample id="3" timestamp="1341761910476"><joint name="HEAD"><x>205.69435</x><y>199.33145</y><z>2422.1887</z><a>1.0</a></joint><joint name="NECK"><x>209.49474</x><y>250.02513</y><z>2435.2207</z><a>1.0</a></joint><joint name="TORSO"><x>210.20818</x><y>292.56158</y><z>2413.0955</z><a>1.0</a></joint><joint name="LEFT_SHOULDER"><x>183.75589</x><y>251.82301</y><z>2463.2026</z><a>1.0</a></joint><joint name="LEFT_ELBOW"><x>169.76399</x><y>297.90564</y><z>2460.0293</z><a>1.0</a></joint><joint name="LEFT_HAND"><x>147.63667</x><y>373.88544</y><z>2199.7239</z><a>1.0</a></joint><joint name="RIGHT_SHOULDER"><x>235.83194</x><y>248.18544</y><z>2407.2385</z><a>1.0</a></joint><joint name="RIGHT_ELBOW"><x>250.64983</x><y>303.58347</y><z>2394.4407</z><a>1.0</a></joint><joint name="RIGHT_HAND"><x>241.71431</x><y>374.5975</y><z>2190.5662</z><a>1.0</a></joint><joint name="LEFT_HIP"><x>192.86325</x><y>336.46237</y><z>2410.1816</z><a>1.0</a></joint><joint name="LEFT_KNEE"><x>191.00337</x><y>425.3194</y><z>2429.4568</z><a>1.0</a></joint><joint name="LEFT_FOOT"><x>187.44472</x><y>486.85193</y><z>2229.923</z><a>1.0</a></joint><joint name="RIGHT_HIP"><x>229.29916</x><y>335.29877</y><z>2371.7588</z><a>1.0</a></joint><joint name="RIGHT_KNEE"><x>202.39445</x><y>401.92667</y><z>2027.7595</z><a>1.0</a></joint><joint name="RIGHT_FOOT"><x>209.00081</x><y>474.3449</y><z>2174.4424</z><a>1.0</a></joint></sample><sample id="3" timestamp="1341761910551"><joint name="HEAD"><x>206.00677</x><y>199.46173</y><z>2425.0835</z><a>1.0</a></joint><joint name="NECK"><x>209.93713</x><y>250.03108</y><z>2439.3208</z><a>1.0</a></joint><joint name="TORSO"><x>210.68304</x><y>292.4504</y><z>2417.644</z><a>1.0</a></joint><joint name="LEFT_SHOULDER"><x>184.09726</x><y>251.80872</y><z>2466.7651</z><a>1.0</a></joint><joint name="LEFT_ELBOW"><x>170.26727</x><y>298.43127</y><z>2457.9524</z><a>1.0</a></joint><joint name="LEFT_HAND"><x>154.67453</x><y>365.97836</y><z>2229.6912</z><a>1.0</a></joint><joint name="RIGHT_SHOULDER"><x>236.36507</x><y>248.21298</y><z>2411.8767</z><a>1.0</a></joint><joint name="RIGHT_ELBOW"><x>249.09914</x><y>305.28894</y><z>2411.1128</z><a>1.0</a></joint><joint name="RIGHT_HAND"><x>242.05566</x><y>371.42618</y><z>2199.0254</z><a>1.0</a></joint><joint name="LEFT_HIP"><x>193.60146</x><y>336.20667</y><z>2414.5024</z><a>1.0</a></joint><joint name="LEFT_KNEE"><x>191.99522</x><y>425.0332</y><z>2436.5217</z><a>1.0</a></joint><joint name="LEFT_FOOT"><x>190.04747</x><y>487.06223</y><z>2230.683</z><a>1.0</a></joint><joint name="RIGHT_HIP"><x>229.56165</x><y>335.059</y><z>2377.432</z><a>1.0</a></joint><joint name="RIGHT_KNEE"><x>202.84993</x><y>400.8619</y><z>2031.3357</z><a>1.0</a></joint><joint name="RIGHT_FOOT"><x>202.83575</x><y>480.84058</y><z>2253.4922</z><a>1.0</a></joint></sample><sample id="3" timestamp="1341761910656"><joint name="HEAD"><x>206.66846</x><y>200.2721</y><z>2436.8225</z><a>1.0</a></joint><joint name="NECK"><x>209.93053</x><y>251.17995</y><z>2440.6743</z><a>1.0</a></joint><joint name="TORSO"><x>211.8069</x><y>292.648</y><z>2418.605</z><a>1.0</a></joint><joint name="LEFT_SHOULDER"><x>183.5211</x><y>253.742</y><z>2466.2812</z><a>1.0</a></joint><joint name="LEFT_ELBOW"><x>170.94342</x><y>300.23666</y><z>2456.8599</z><a>1.0</a></joint><joint name="LEFT_HAND"><x>151.50806</x><y>370.98572</y><z>2218.6157</z><a>1.0</a></joint><joint name="RIGHT_SHOULDER"><x>236.9</x><y>248.56357</y><z>2415.0674</z><a>1.0</a></joint><joint name="RIGHT_ELBOW"><x>249.5195</x><y>308.05023</y><z>2430.1313</z><a>1.0</a></joint><joint name="RIGHT_HAND"><x>242.06789</x><y>372.0368</y><z>2204.185</z><a>1.0</a></joint><joint name="LEFT_HIP"><x>194.89748</x><y>336.0845</y><z>2414.3735</z><a>1.0</a></joint><joint name="LEFT_KNEE"><x>193.91338</x><y>427.32745</y><z>2429.6013</z><a>1.0</a></joint><joint name="LEFT_FOOT"><x>193.25386</x><y>493.60614</y><z>2256.229</z><a>1.0</a></joint><joint name="RIGHT_HIP"><x>232.82048</x><y>333.657</y><z>2378.6978</z><a>1.0</a></joint><joint name="RIGHT_KNEE"><x>202.92064</x><y>398.1198</y><z>2036.5763</z><a>1.0</a></joint><joint name="RIGHT_FOOT"><x>208.64406</x><y>475.50656</y><z>2187.947</z><a>1.0</a></joint></sample><sample id="3" timestamp="1341761910742"><joint name="HEAD"><x>206.46515</x><y>199.99286</y><z>2441.3418</z><a>1.0</a></joint><joint name="NECK"><x>209.21864</x><y>251.8584</y><z>2441.3193</z><a>1.0</a></joint><joint name="TORSO"><x>211.62</x><y>293.29572</y><z>2422.5771</z><a>1.0</a></joint><joint name="LEFT_SHOULDER"><x>182.04578</x><y>254.5353</y><z>2463.7102</z><a>1.0</a></joint><joint name="LEFT_ELBOW"><x>169.98024</x><y>303.84595</y><z>2455.155</z><a>1.0</a></joint><joint name="LEFT_HAND"><x>146.02547</x><y>375.82422</y><z>2210.5117</z><a>1.0</a></joint><joint name="RIGHT_SHOULDER"><x>236.89458</x><y>249.13196</y><z>2418.9285</z><a>1.0</a></joint><joint name="RIGHT_ELBOW"><x>249.71771</x><y>308.01675</y><z>2430.8513</z><a>1.0</a></joint><joint name="RIGHT_HAND"><x>241.57683</x><y>373.54166</y><z>2204.3723</z><a>1.0</a></joint><joint name="LEFT_HIP"><x>195.69203</x><y>336.67337</y><z>2418.6687</z><a>1.0</a></joint><joint name="LEFT_KNEE"><x>170.85802</x><y>403.34378</y><z>2077.5857</z><a>1.0</a></joint><joint name="LEFT_FOOT"><x>194.24106</x><y>487.56067</y><z>2262.3125</z><a>1.0</a></joint><joint name="RIGHT_HIP"><x>232.65363</x><y>334.06888</y><z>2389.0012</z><a>1.0</a></joint><joint name="RIGHT_KNEE"><x>202.30084</x><y>397.05078</y><z>2035.3142</z><a>1.0</a></joint><joint name="RIGHT_FOOT"><x>210.48262</x><y>474.74683</y><z>2181.29</z><a>1.0</a></joint></sample><sample id="3" timestamp="1341761910850"><joint name="HEAD"><x>206.46242</x><y>200.2232</y><z>2445.881</z><a>1.0</a></joint><joint name="NECK"><x>208.73761</x><y>252.33093</y><z>2439.874</z><a>1.0</a></joint><joint name="TORSO"><x>211.14066</x><y>293.77393</y><z>2420.0725</z><a>1.0</a></joint><joint name="LEFT_SHOULDER"><x>181.49532</x><y>255.08553</y><z>2462.4863</z><a>1.0</a></joint><joint name="LEFT_ELBOW"><x>168.44888</x><y>306.97214</y><z>2457.4646</z><a>1.0</a></joint><joint name="LEFT_HAND"><x>148.25824</x><y>372.2705</y><z>2229.816</z><a>1.0</a></joint><joint name="RIGHT_SHOULDER"><x>236.48956</x><y>249.5248</y><z>2417.2617</z><a>1.0</a></joint><joint name="RIGHT_ELBOW"><x>249.48451</x><y>308.48132</y><z>2424.7695</z><a>1.0</a></joint><joint name="RIGHT_HAND"><x>242.95932</x><y>371.60123</y><z>2203.131</z><a>1.0</a></joint><joint name="LEFT_HIP"><x>195.12729</x><y>337.24478</y><z>2415.2722</z><a>1.0</a></joint><joint name="LEFT_KNEE"><x>166.54765</x><y>402.85284</y><z>2050.4822</z><a>1.0</a></joint><joint name="LEFT_FOOT"><x>188.63873</x><y>473.4397</y><z>2228.0557</z><a>1.0</a></joint><joint name="RIGHT_HIP"><x>232.27153</x><y>334.5397</y><z>2385.27</z><a>1.0</a></joint><joint name="RIGHT_KNEE"><x>201.8792</x><y>395.45062</y><z>2036.7307</z><a>1.0</a></joint><joint name="RIGHT_FOOT"><x>209.3633</x><y>474.28558</y><z>2185.81</z><a>1.0</a></joint></sample><sample id="3" timestamp="1341761910927"><joint name="HEAD"><x>206.21503</x><y>199.76143</y><z>2445.0005</z><a>1.0</a></joint><joint name="NECK"><x>208.07373</x><y>252.00153</y><z>2436.201</z><a>1.0</a></joint><joint name="TORSO"><x>210.9301</x><y>293.3221</y><z>2418.3042</z><a>1.0</a></joint><joint name="LEFT_SHOULDER"><x>180.90056</x><y>255.06769</y><z>2463.5222</z><a>1.0</a></joint><joint name="LEFT_ELBOW"><x>168.08797</x><y>307.72113</y><z>2466.6401</z><a>1.0</a></joint><joint name="LEFT_HAND"><x>148.24556</x><y>375.59457</y><z>2232.444</z><a>1.0</a></joint><joint name="RIGHT_SHOULDER"><x>235.86328</x><y>248.8658</y><z>2408.8796</z><a>1.0</a></joint><joint name="RIGHT_ELBOW"><x>248.94186</x><y>308.1699</y><z>2419.8901</z><a>1.0</a></joint><joint name="RIGHT_HAND"><x>241.61209</x><y>370.5721</y><z>2194.8262</z><a>1.0</a></joint><joint name="LEFT_HIP"><x>195.6658</x><y>336.68784</y><z>2418.2925</z><a>1.0</a></joint><joint name="LEFT_KNEE"><x>167.9572</x><y>405.1157</y><z>2056.2898</z><a>1.0</a></joint><joint name="LEFT_FOOT"><x>188.21457</x><y>476.2227</y><z>2236.8137</z><a>1.0</a></joint><joint name="RIGHT_HIP"><x>232.26506</x><y>333.80844</y><z>2382.5225</z><a>1.0</a></joint><joint name="RIGHT_KNEE"><x>203.09138</x><y>395.65292</y><z>2041.2994</z><a>1.0</a></joint><joint name="RIGHT_FOOT"><x>208.52068</x><y>474.56802</y><z>2187.071</z><a>1.0</a></joint></sample><sample id="3" timestamp="1341761911022"><joint name="HEAD"><x>206.1596</x><y>199.45514</y><z>2446.431</z><a>1.0</a></joint><joint name="NECK"><x>208.09567</x><y>251.82805</y><z>2436.8826</z><a>1.0</a></joint><joint name="TORSO"><x>211.01038</x><y>293.12534</y><z>2419.6743</z><a>1.0</a></joint><joint name="LEFT_SHOULDER"><x>181.15721</x><y>254.91269</y><z>2466.1992</z><a>1.0</a></joint><joint name="LEFT_ELBOW"><x>167.64445</x><y>307.62628</y><z>2469.546</z><a>1.0</a></joint><joint name="LEFT_HAND"><x>148.8664</x><y>374.32462</y><z>2231.8025</z><a>1.0</a></joint><joint name="RIGHT_SHOULDER"><x>235.69017</x><y>248.66827</y><z>2407.5657</z><a>1.0</a></joint><joint name="RIGHT_ELBOW"><x>248.56142</x><y>308.05334</y><z>2421.5051</z><a>1.0</a></joint><joint name="RIGHT_HAND"><x>241.06717</x><y>361.5041</y><z>2218.4026</z><a>1.0</a></joint><joint name="LEFT_HIP"><x>195.68312</x><y>336.43298</y><z>2421.9565</z><a>1.0</a></joint><joint name="LEFT_KNEE"><x>167.56267</x><y>405.25095</y><z>2057.2834</z><a>1.0</a></joint><joint name="LEFT_FOOT"><x>187.65143</x><y>474.8075</y><z>2233.4124</z><a>1.0</a></joint><joint name="RIGHT_HIP"><x>232.54964</x><y>333.57224</y><z>2382.9756</z><a>1.0</a></joint><joint name="RIGHT_KNEE"><x>203.17749</x><y>395.6714</y><z>2042.2264</z><a>1.0</a></joint><joint name="RIGHT_FOOT"><x>206.63757</x><y>473.21634</y><z>2188.3381</z><a>1.0</a></joint></sample><sample id="3" timestamp="1341761911130"><joint name="HEAD"><x>205.54303</x><y>198.63383</y><z>2447.7344</z><a>1.0</a></joint><joint name="NECK"><x>207.6496</x><y>251.27214</y><z>2434.905</z><a>1.0</a></joint><joint name="TORSO"><x>210.45064</x><y>292.36606</y><z>2422.1968</z><a>1.0</a></joint><joint name="LEFT_SHOULDER"><x>180.1946</x><y>253.97716</y><z>2461.5007</z><a>1.0</a></joint><joint name="LEFT_ELBOW"><x>166.33444</x><y>306.42007</y><z>2469.9246</z><a>1.0</a></joint><joint name="LEFT_HAND"><x>147.05852</x><y>373.50613</y><z>2239.9956</z><a>1.0</a></joint><joint name="RIGHT_SHOULDER"><x>235.71097</x><y>248.50739</y><z>2408.309</z><a>1.0</a></joint><joint name="RIGHT_ELBOW"><x>247.98894</x><y>307.13736</y><z>2429.2756</z><a>1.0</a></joint><joint name="RIGHT_HAND"><x>242.64207</x><y>365.4378</y><z>2221.5864</z><a>1.0</a></joint><joint name="LEFT_HIP"><x>195.07594</x><y>335.09256</y><z>2426.8374</z><a>1.0</a></joint><joint name="LEFT_KNEE"><x>171.32924</x><y>401.61188</y><z>2062.1682</z><a>1.0</a></joint><joint name="LEFT_FOOT"><x>187.43005</x><y>476.61102</y><z>2208.935</z><a>1.0</a></joint><joint name="RIGHT_HIP"><x>231.75058</x><y>332.677</y><z>2392.14</z><a>1.0</a></joint><joint name="RIGHT_KNEE"><x>203.36853</x><y>396.41843</y><z>2039.306</z><a>1.0</a></joint><joint name="RIGHT_FOOT"><x>204.95944</x><y>472.91437</y><z>2184.505</z><a>1.0</a></joint></sample><sample id="3" timestamp="1341761911208"><joint name="HEAD"><x>205.4134</x><y>198.36014</y><z>2447.7954</z><a>1.0</a></joint><joint name="NECK"><x>207.44212</x><y>251.04056</y><z>2434.9658</z><a>1.0</a></joint><joint name="TORSO"><x>210.48703</x><y>291.93106</y><z>2422.0466</z><a>1.0</a></joint><joint name="LEFT_SHOULDER"><x>180.02649</x><y>253.94792</y><z>2461.7114</z><a>1.0</a></joint><joint name="LEFT_ELBOW"><x>166.21965</x><y>306.34448</y><z>2469.0542</z><a>1.0</a></joint><joint name="LEFT_HAND"><x>145.19122</x><y>384.73874</y><z>2189.978</z><a>1.0</a></joint><joint name="RIGHT_SHOULDER"><x>235.46672</x><y>248.0686</y><z>2408.2202</z><a>1.0</a></joint><joint name="RIGHT_ELBOW"><x>248.02293</x><y>306.43994</y><z>2431.0427</z><a>1.0</a></joint><joint name="RIGHT_HAND"><x>243.19922</x><y>366.6269</y><z>2215.4197</z><a>1.0</a></joint><joint name="LEFT_HIP"><x>195.06676</x><y>334.6158</y><z>2426.8748</z><a>1.0</a></joint><joint name="LEFT_KNEE"><x>170.30168</x><y>402.02557</y><z>2062.3867</z><a>1.0</a></joint><joint name="LEFT_FOOT"><x>188.76067</x><y>474.80215</y><z>2218.8728</z><a>1.0</a></joint><joint name="RIGHT_HIP"><x>232.33702</x><y>331.88437</y><z>2391.3801</z><a>1.0</a></joint><joint name="RIGHT_KNEE"><x>204.93286</x><y>396.085</y><z>2041.1975</z><a>1.0</a></joint><joint name="RIGHT_FOOT"><x>205.63205</x><y>473.7859</y><z>2183.1946</z><a>1.0</a></joint></sample><sample id="3" timestamp="1341761911314"><joint name="HEAD"><x>204.95422</x><y>198.3263</y><z>2445.8994</z><a>1.0</a></joint><joint name="NECK"><x>207.10178</x><y>250.405</y><z>2431.9783</z><a>1.0</a></joint><joint name="TORSO"><x>210.39516</x><y>291.2563</y><z>2420.189</z><a>1.0</a></joint><joint name="LEFT_SHOULDER"><x>179.92015</x><y>253.4064</y><z>2459.2136</z><a>1.0</a></joint><joint name="LEFT_ELBOW"><x>166.24223</x><y>305.5909</y><z>2469.6064</z><a>1.0</a></joint><joint name="LEFT_HAND"><x>149.08882</x><y>364.95343</y><z>2267.8916</z><a>1.0</a></joint><joint name="RIGHT_SHOULDER"><x>234.8991</x><y>247.3356</y><z>2404.7432</z><a>1.0</a></joint><joint name="RIGHT_ELBOW"><x>247.86554</x><y>306.09146</y><z>2428.819</z><a>1.0</a></joint><joint name="RIGHT_HAND"><x>242.67252</x><y>363.20795</y><z>2224.503</z><a>1.0</a></joint><joint name="LEFT_HIP"><x>194.67528</x><y>333.9695</y><z>2427.1833</z><a>1.0</a></joint><joint name="LEFT_KNEE"><x>167.51472</x><y>402.37708</y><z>2058.237</z><a>1.0</a></joint><joint name="LEFT_FOOT"><x>189.92072</x><y>471.42035</y><z>2239.9924</z><a>1.0</a></joint><joint name="RIGHT_HIP"><x>233.06569</x><y>331.02258</y><z>2389.6157</z><a>1.0</a></joint><joint name="RIGHT_KNEE"><x>205.16394</x><y>393.721</y><z>2040.8911</z><a>1.0</a></joint><joint name="RIGHT_FOOT"><x>206.98497</x><y>471.9722</y><z>2177.3604</z><a>1.0</a></joint></sample><sample id="3" timestamp="1341761911389"><joint name="HEAD"><x>204.61632</x><y>198.32968</y><z>2445.602</z><a>1.0</a></joint><joint name="NECK"><x>207.14159</x><y>250.08282</y><z>2430.6445</z><a>1.0</a></joint><joint name="TORSO"><x>210.39342</x><y>291.18402</y><z>2419.686</z><a>1.0</a></joint><joint name="LEFT_SHOULDER"><x>180.0031</x><y>252.98337</y><z>2458.2166</z><a>1.0</a></joint><joint name="LEFT_ELBOW"><x>166.65901</x><y>304.42416</y><z>2471.111</z><a>1.0</a></joint><joint name="LEFT_HAND"><x>150.02577</x><y>365.30527</y><z>2273.3086</z><a>1.0</a></joint><joint name="RIGHT_SHOULDER"><x>234.90283</x><y>247.1157</y><z>2403.0725</z><a>1.0</a></joint><joint name="RIGHT_ELBOW"><x>247.73985</x><y>305.82706</y><z>2426.2703</z><a>1.0</a></joint><joint name="RIGHT_HAND"><x>242.67642</x><y>364.68964</y><z>2217.718</z><a>1.0</a></joint><joint name="LEFT_HIP"><x>194.5614</x><y>334.04596</y><z>2427.8547</z><a>1.0</a></joint><joint name="LEFT_KNEE"><x>165.77321</x><y>399.7683</y><z>2053.916</z><a>1.0</a></joint><joint name="LEFT_FOOT"><x>189.07057</x><y>470.5419</y><z>2235.714</z><a>1.0</a></joint><joint name="RIGHT_HIP"><x>233.09422</x><y>331.2502</y><z>2389.6</z><a>1.0</a></joint><joint name="RIGHT_KNEE"><x>205.0651</x><y>393.64764</y><z>2042.4735</z><a>1.0</a></joint><joint name="RIGHT_FOOT"><x>206.24895</x><y>472.17056</y><z>2177.8704</z><a>1.0</a></joint></sample><sample id="3" timestamp="1341761911495"><joint name="HEAD"><x>203.26154</x><y>198.03827</y><z>2444.2334</z><a>1.0</a></joint><joint name="NECK"><x>206.94383</x><y>250.1873</y><z>2430.2734</z><a>1.0</a></joint><joint name="TORSO"><x>209.99602</x><y>291.28375</y><z>2419.4448</z><a>1.0</a></joint><joint name="LEFT_SHOULDER"><x>179.38397</x><y>252.93324</y><z>2454.7883</z><a>1.0</a></joint><joint name="LEFT_ELBOW"><x>166.72363</x><y>304.63553</y><z>2473.8987</z><a>1.0</a></joint><joint name="LEFT_HAND"><x>147.32834</x><y>367.44467</y><z>2268.0637</z><a>1.0</a></joint><joint name="RIGHT_SHOULDER"><x>235.06537</x><y>247.38539</y><z>2405.7585</z><a>1.0</a></joint><joint name="RIGHT_ELBOW"><x>248.55223</x><y>306.0706</y><z>2417.6045</z><a>1.0</a></joint><joint name="RIGHT_HAND"><x>242.81438</x><y>366.9161</y><z>2213.773</z><a>1.0</a></joint><joint name="LEFT_HIP"><x>193.89917</x><y>334.08368</y><z>2425.4326</z><a>1.0</a></joint><joint name="LEFT_KNEE"><x>166.1397</x><y>402.13406</y><z>2052.7063</z><a>1.0</a></joint><joint name="LEFT_FOOT"><x>189.22952</x><y>469.67914</y><z>2244.5398</z><a>1.0</a></joint><joint name="RIGHT_HIP"><x>232.52176</x><y>331.39694</y><z>2391.7998</z><a>1.0</a></joint><joint name="RIGHT_KNEE"><x>205.31865</x><y>394.7631</y><z>2041.614</z><a>1.0</a></joint><joint name="RIGHT_FOOT"><x>210.53415</x><y>473.53568</y><z>2207.5469</z><a>1.0</a></joint></sample><sample id="3" timestamp="1341761911576"><joint name="HEAD"><x>203.22324</x><y>198.09042</y><z>2443.5933</z><a>1.0</a></joint><joint name="NECK"><x>206.92538</x><y>250.20497</y><z>2430.9468</z><a>1.0</a></joint><joint name="TORSO"><x>209.99483</x><y>291.40997</y><z>2418.794</z><a>1.0</a></joint><joint name="LEFT_SHOULDER"><x>179.41183</x><y>253.03177</y><z>2455.0205</z><a>1.0</a></joint><joint name="LEFT_ELBOW"><x>167.00697</x><y>304.62546</y><z>2476.533</z><a>1.0</a></joint><joint name="LEFT_HAND"><x>150.48645</x><y>364.2738</y><z>2285.6365</z><a>1.0</a></joint><joint name="RIGHT_SHOULDER"><x>234.98935</x><y>247.32164</y><z>2406.8733</z><a>1.0</a></joint><joint name="RIGHT_ELBOW"><x>247.99956</x><y>306.61627</y><z>2412.4614</z><a>1.0</a></joint><joint name="RIGHT_HAND"><x>242.88306</x><y>368.49582</y><z>2208.8699</z><a>1.0</a></joint><joint name="LEFT_HIP"><x>193.89137</x><y>334.43417</y><z>2423.1897</z><a>1.0</a></joint><joint name="LEFT_KNEE"><x>166.42537</x><y>402.77762</y><z>2050.8833</z><a>1.0</a></joint><joint name="LEFT_FOOT"><x>193.48189</x><y>470.66058</y><z>2237.2476</z><a>1.0</a></joint><joint name="RIGHT_HIP"><x>232.5651</x><y>331.6086</y><z>2390.0925</z><a>1.0</a></joint><joint name="RIGHT_KNEE"><x>205.2137</x><y>394.93082</y><z>2042.0001</z><a>1.0</a></joint><joint name="RIGHT_FOOT"><x>211.56755</x><y>472.48715</y><z>2212.7268</z><a>1.0</a></joint></sample><sample id="3" timestamp="1341761911666"><joint name="HEAD"><x>202.88771</x><y>198.07407</y><z>2440.5217</z><a>1.0</a></joint><joint name="NECK"><x>206.48502</x><y>250.14128</y><z>2431.0217</z><a>1.0</a></joint><joint name="TORSO"><x>209.80467</x><y>291.48843</y><z>2418.5767</z><a>1.0</a></joint><joint name="LEFT_SHOULDER"><x>178.86957</x><y>253.08955</y><z>2450.7712</z><a>1.0</a></joint><joint name="LEFT_ELBOW"><x>167.5477</x><y>305.1735</y><z>2479.2937</z><a>1.0</a></joint><joint name="LEFT_HAND"><x>145.73067</x><y>371.97253</y><z>2254.1807</z><a>1.0</a></joint><joint name="RIGHT_SHOULDER"><x>234.55283</x><y>247.1447</y><z>2411.2722</z><a>1.0</a></joint><joint name="RIGHT_ELBOW"><x>247.00877</x><y>305.65027</y><z>2413.614</z><a>1.0</a></joint><joint name="RIGHT_HAND"><x>242.4702</x><y>368.37274</y><z>2201.867</z><a>1.0</a></joint><joint name="LEFT_HIP"><x>193.51767</x><y>334.88065</y><z>2419.9746</z><a>1.0</a></joint><joint name="LEFT_KNEE"><x>168.9527</x><y>405.55414</y><z>2049.0679</z><a>1.0</a></joint><joint name="LEFT_FOOT"><x>187.37393</x><y>479.7419</y><z>2205.195</z><a>1.0</a></joint><joint name="RIGHT_HIP"><x>233.027</x><y>331.62723</y><z>2392.2886</z><a>1.0</a></joint><joint name="RIGHT_KNEE"><x>205.9553</x><y>395.15103</y><z>2045.0083</z><a>1.0</a></joint><joint name="RIGHT_FOOT"><x>207.12057</x><y>474.08823</y><z>2183.156</z><a>1.0</a></joint></sample><sample id="3" timestamp="1341761911736"><joint name="HEAD"><x>202.72664</x><y>198.36137</y><z>2439.9668</z><a>1.0</a></joint><joint name="NECK"><x>206.42442</x><y>249.70924</y><z>2429.4446</z><a>1.0</a></joint><joint name="TORSO"><x>209.7425</x><y>291.2454</y><z>2418.4387</z><a>1.0</a></joint><joint name="LEFT_SHOULDER"><x>178.72247</x><y>252.5597</y><z>2448.5615</z><a>1.0</a></joint><joint name="LEFT_ELBOW"><x>168.06805</x><y>304.80887</y><z>2480.9988</z><a>1.0</a></joint><joint name="LEFT_HAND"><x>148.19</x><y>369.09262</y><z>2268.5554</z><a>1.0</a></joint><joint name="RIGHT_SHOULDER"><x>234.56578</x><y>246.81357</y><z>2410.3276</z><a>1.0</a></joint><joint name="RIGHT_ELBOW"><x>246.91284</x><y>305.4851</y><z>2414.263</z><a>1.0</a></joint><joint name="RIGHT_HAND"><x>242.66759</x><y>368.92093</y><z>2198.7727</z><a>1.0</a></joint><joint name="LEFT_HIP"><x>193.46712</x><y>334.7161</y><z>2420.7964</z><a>1.0</a></joint><joint name="LEFT_KNEE"><x>168.32224</x><y>405.3793</y><z>2049.5984</z><a>1.0</a></joint><joint name="LEFT_FOOT"><x>186.91927</x><y>488.17413</y><z>2186.6633</z><a>1.0</a></joint><joint name="RIGHT_HIP"><x>232.9338</x><y>331.5892</y><z>2394.0693</z><a>1.0</a></joint><joint name="RIGHT_KNEE"><x>205.83437</x><y>394.8627</y><z>2045.1016</z><a>1.0</a></joint><joint name="RIGHT_FOOT"><x>207.4156</x><y>473.72034</y><z>2184.875</z><a>1.0</a></joint></sample><sample id="3" timestamp="1341761911835"><joint name="HEAD"><x>202.62729</x><y>198.51398</y><z>2439.8894</z><a>1.0</a></joint><joint name="NECK"><x>206.32709</x><y>249.54428</y><z>2428.311</z><a>1.0</a></joint><joint name="TORSO"><x>209.63951</x><y>291.00647</y><z>2418.61</z><a>1.0</a></joint><joint name="LEFT_SHOULDER"><x>178.7833</x><y>252.32251</y><z>2448.5952</z><a>1.0</a></joint><joint name="LEFT_ELBOW"><x>168.43921</x><y>304.16525</y><z>2483.0522</z><a>1.0</a></joint><joint name="LEFT_HAND"><x>153.28174</x><y>349.5924</y><z>2320.45</z><a>1.0</a></joint><joint name="RIGHT_SHOULDER"><x>234.33492</x><y>246.71924</y><z>2408.027</z><a>1.0</a></joint><joint name="RIGHT_ELBOW"><x>246.75574</x><y>305.5553</y><z>2417.3984</z><a>1.0</a></joint><joint name="RIGHT_HAND"><x>243.46655</x><y>368.7899</y><z>2202.8823</z><a>1.0</a></joint><joint name="LEFT_HIP"><x>193.71675</x><y>334.26022</y><z>2422.9172</z><a>1.0</a></joint><joint name="LEFT_KNEE"><x>168.31335</x><y>405.0025</y><z>2050.1897</z><a>1.0</a></joint><joint name="LEFT_FOOT"><x>186.73703</x><y>482.84818</y><z>2205.0996</z><a>1.0</a></joint><joint name="RIGHT_HIP"><x>232.46582</x><y>331.3279</y><z>2394.901</z><a>1.0</a></joint><joint name="RIGHT_KNEE"><x>205.70534</x><y>395.09604</y><z>2042.5247</z><a>1.0</a></joint><joint name="RIGHT_FOOT"><x>206.9654</x><y>473.01483</y><z>2186.6663</z><a>1.0</a></joint></sample></session>